CHANGES.txt
MANIFEST.in
README.rst
setup.py
tomcom/__init__.py
tomcom.browsers.base.egg-info/PKG-INFO
tomcom.browsers.base.egg-info/SOURCES.txt
tomcom.browsers.base.egg-info/dependency_links.txt
tomcom.browsers.base.egg-info/entry_points.txt
tomcom.browsers.base.egg-info/namespace_packages.txt
tomcom.browsers.base.egg-info/not-zip-safe
tomcom.browsers.base.egg-info/requires.txt
tomcom.browsers.base.egg-info/top_level.txt
tomcom/browsers/__init__.py
tomcom/browsers/base/__init__.py
tomcom/browsers/base/tests/__init__.py
tomcom/browsers/base/tests/test_base.py