Metadata-Version: 1.1
Name: tomcom.browsers.base
Version: 2.13.21.2
Summary: Reduce seperate importing of browser requirements
Home-page: https://github.com/tomcom-de/tomcom.browsers.base.git
Author: Tomcom GmbH
Author-email: info@tomcom.de
License: GPL version 2
Keywords: browser base tomcom
Platform: Any
Classifier: Development Status :: 5 - Production/Stable
Classifier: Environment :: Web Environment
Classifier: Framework :: Plone
Classifier: Framework :: Zope2
Classifier: Intended Audience :: Other Audience
Classifier: Intended Audience :: System Administrators
Classifier: License :: OSI Approved :: GNU General Public License (GPL)
Classifier: Operating System :: OS Independent
Classifier: Programming Language :: Python
Classifier: Topic :: Internet :: WWW/HTTP :: Site Management :: Link Checking
